ngslab/__init__.py
ngslab/const.py
ngslab/mat.py
ngslab/model.py
ngslab/plot.py
ngslab/demo/4layer_lossy_tmatrix.txt
ngslab/demo/4layer_tmatrix.txt
ngslab/demo/Rakic 1998 - Au (LD model).py
ngslab/demo/Rakic1998_AgDrude.py
ngslab/demo/Rosenblatt2010_DrudeAu.py
ngslab/demo/agDrude.ref
ngslab/demo/agjc.ref
ngslab/demo/auDrude.ref
ngslab/demo/aujc.ref
ngslab/demo/demo_4layer.pdf
ngslab/demo/demo_4layer.py
ngslab/demo/demo_4layer_lossy.pdf
ngslab/demo/demo_4layer_vsPML.py
ngslab/demo/demo_4layerpml_params_-2_10.pdf
ngslab/demo/demo_4layerpml_params_10_10.pdf
ngslab/demo/demo_AgSiO2.pdf
ngslab/demo/demo_AgSiO2.py
ngslab/demo/demo_AuTiO2.py
ngslab/demo/demo_DMD.pdf
ngslab/demo/demo_DMD.py
ngslab/demo/demo_MDM.pdf
ngslab/demo/demo_MDM.py
ngslab/demo/demo_interface.py
ngslab-1.0.1.dist-info/LICENSE
ngslab-1.0.1.dist-info/METADATA
ngslab-1.0.1.dist-info/WHEEL
ngslab-1.0.1.dist-info/top_level.txt
ngslab-1.0.1.dist-info/RECORD
