Metadata-Version: 2.1
Name: ngslab
Version: 1.0.1
Summary: ngslab calculates waveguide modes in an unbounded multilayer planar waveguide using FEM with either PMLs or TBCs.
Author-email: shelvon <xiaorun.zang@outlook.com>
License: GNU LESSER GENERAL PUBLIC LICENSE
Keywords: FEM,NGSolve,TBC,PML,waveguide,mode,slab
Requires-Python: >=3.8
License-File: LICENSE
Requires-Dist: numpy
Requires-Dist: scipy
Requires-Dist: matplotlib
Requires-Dist: petsc4py
Requires-Dist: slepc4py
Requires-Dist: ngsolve
